{
  "metadata": {
    "version": "1.0",
    "last_updated": "2025-07-14T15:12:54.336Z"
  },
  "errors": {
    "-1": {
      "key": "_1",
      "message": "Unknown error",
      "service": "marketplace"
    },
    "-100": {
      "key": "auction_not_exist",
      "message": "Order not exist",
      "service": "marketplace"
    },
    "-101": {
      "key": "auction_status_error",
      "message": "Order status error",
      "service": "marketplace"
    },
    "-102": {
      "key": "bid_not_exist",
      "message": "Resource not available, please try again",
      "service": "marketplace"
    },
    "-104": {
      "key": "not_avaiable_utxo",
      "message": "Available balance not enough",
      "service": "marketplace"
    },
    "-105": {
      "key": "auction_create_error",
      "message": "Auction creation failed",
      "service": "marketplace"
    },
    "-106": {
      "key": "maintain",
      "message": "The system is under maintenance",
      "service": "marketplace"
    },
    "-107": {
      "key": "nft_invalid",
      "message": "Invalid NFT",
      "service": "marketplace"
    },
    "-109": {
      "key": "inscription_not_found",
      "message": "Inscription not found, please try again later",
      "service": "marketplace"
    },
    "-110": {
      "key": "inscription_invalid",
      "message": "Invalid inscription",
      "service": "marketplace"
    },
    "-111": {
      "key": "inscription_info_fail",
      "message": "Failed to get inscription info",
      "service": "marketplace"
    },
    "-112": {
      "key": "sign_error",
      "message": "Sign error",
      "service": "marketplace"
    },
    "-113": {
      "key": "bind_error",
      "message": "If you use the receive address, you need to bind first",
      "service": "marketplace"
    },
    "-114": {
      "key": "domain_char_limit",
      "message": "The domain name contains temporarily unsupported characters",
      "service": "marketplace"
    },
    "-115": {
      "key": "domain_sats_verify_error",
      "message": "Verify domain name error",
      "service": "marketplace"
    },
    "-116": {
      "key": "readonly",
      "message": "The marketplace is currently not operational",
      "service": "marketplace"
    },
    "-118": {
      "key": "transaction_not_found",
      "message": "Transaction not found",
      "service": "marketplace"
    },
    "-119": {
      "key": "indexer_api_error",
      "message": "Indexer error, please try again later",
      "service": "marketplace"
    },
    "-122": {
      "key": "fee_rate_too_low",
      "message": "Fee rate too low",
      "service": "marketplace"
    },
    "-124": {
      "key": "address_type_not_supoort",
      "message": "Address type not supported",
      "service": "marketplace"
    },
    "-126": {
      "key": "invalid_nft_multi_inscriptions",
      "message": "Invalid NFT: multi inscriptions",
      "service": "marketplace"
    },
    "-127": {
      "key": "invalid_nft_not_confirmed",
      "message": "Invalid NFT: not confirmed",
      "service": "marketplace"
    },
    "-131": {
      "key": "buyers_sellers_is_same",
      "message": "Buyer and seller cannot be the same one",
      "service": "marketplace"
    },
    "-132": {
      "key": "minimum_selling_price",
      "message": "The lowest listing amount of satoshis is {value}",
      "service": "marketplace",
      "has_variable": true
    },
    "-133": {
      "key": "highest_selling_price",
      "message": "The highest listing amount of satoshis is {value}",
      "service": "marketplace",
      "has_variable": true
    },
    "-137": {
      "key": "first_bid_price_error",
      "message": "First bid price error",
      "service": "marketplace"
    },
    "-138": {
      "key": "bid_price_too_low",
      "message": "Bid price too low",
      "service": "marketplace"
    },
    "-139": {
      "key": "fixed_price_error",
      "message": "The price has updated by the seller. Please refresh the page and try again",
      "service": "marketplace"
    },
    "-141": {
      "key": "not_support_in_fixed_price_mode",
      "message": "Not supported in fixed price mode",
      "service": "marketplace"
    },
    "-144": {
      "key": "auction_is_started",
      "message": "The listing is not available anymore",
      "service": "marketplace"
    },
    "-145": {
      "key": "repeat_bid",
      "message": "Repeated operation",
      "service": "marketplace"
    },
    "-147": {
      "key": "not_allowed_to_proceed",
      "message": "You are not allowed to proceed",
      "service": "marketplace"
    },
    "-148": {
      "key": "blacklist_tip",
      "message": "System has detected malicious behavior, contact Discord admin",
      "service": "marketplace"
    },
    "-150": {
      "key": "confirmations_num_to_be_traded",
      "message": "Inscription needs more confirmations to be traded",
      "service": "marketplace"
    },
    "-151": {
      "key": "confirmations_num_to_be_listed",
      "message": "Inscription needs more confirmations to be listed",
      "service": "marketplace"
    },
    "-152": {
      "key": "invalid_nft_unknown_type",
      "message": "Invalid NFT: unknown type",
      "service": "marketplace"
    },
    "-153": {
      "key": "server_busy",
      "message": "The service is busy, please wait",
      "service": "marketplace"
    },
    "-154": {
      "key": "indexer_timeout",
      "message": "Request indexer timeout, please retry",
      "service": "marketplace"
    },
    "-155": {
      "key": "seller_less_than_dust",
      "message": "Inscription value below min threshold (dust)",
      "service": "marketplace"
    },
    "-156": {
      "key": "user_params_error",
      "message": "User params error: {details}",
      "service": "marketplace",
      "has_variable": true
    },
    "-157": {
      "key": "batch_bid_not_support",
      "message": "Bulk purchase not supported",
      "service": "marketplace"
    },
    "-158": {
      "key": "atomicals_api_error",
      "message": "Atomicals API error",
      "service": "marketplace"
    },
    "-159": {
      "key": "buyer_less_than_dust",
      "message": "This address cannot receive the inscription because it is less than dust, please try another address",
      "service": "marketplace"
    },
    "-160": {
      "key": "inscription_listed",
      "message": "Inscription is already listed on the market",
      "service": "marketplace"
    },
    "-161": {
      "key": "service_updated_try_again",
      "message": "The service is being updated, please try again",
      "service": "marketplace"
    },
    "-162": {
      "key": "invalid_utxo",
      "message": "Invalid UTXO",
      "service": "marketplace"
    },
    "-163": {
      "key": "public_address_inconsistent",
      "message": "The public key and address do not match",
      "service": "marketplace"
    },
    "-164": {
      "key": "runes_api_error",
      "message": "Runes API error",
      "service": "marketplace"
    },
    "-165": {
      "key": "invalid_runes",
      "message": "Invalid runes",
      "service": "marketplace"
    },
    "-166": {
      "key": "batch_listing_not_support",
      "message": "Bulk listing does not yet support this type of NFT",
      "service": "marketplace"
    },
    "-167": {
      "key": "dummy_utxo_not_enough",
      "message": "The number of UTXO is not enough",
      "service": "marketplace"
    },
    "-168": {
      "key": "dummy_split_only_support",
      "message": "Splitting UTXO currently only supports p2tr, p2sh, p2wpkh address types",
      "service": "marketplace"
    },
    "-169": {
      "key": "alkanes_api_error",
      "message": "Alkanes API error",
      "service": "marketplace"
    }
  }
}